zendriver_flare_bypasser/__init__.py
zendriver_flare_bypasser/_version.py
zendriver_flare_bypasser/py.typed
zendriver_flare_bypasser/cdp/README.md
zendriver_flare_bypasser/cdp/__init__.py
zendriver_flare_bypasser/cdp/accessibility.py
zendriver_flare_bypasser/cdp/animation.py
zendriver_flare_bypasser/cdp/audits.py
zendriver_flare_bypasser/cdp/autofill.py
zendriver_flare_bypasser/cdp/background_service.py
zendriver_flare_bypasser/cdp/bluetooth_emulation.py
zendriver_flare_bypasser/cdp/browser.py
zendriver_flare_bypasser/cdp/cache_storage.py
zendriver_flare_bypasser/cdp/cast.py
zendriver_flare_bypasser/cdp/console.py
zendriver_flare_bypasser/cdp/css.py
zendriver_flare_bypasser/cdp/database.py
zendriver_flare_bypasser/cdp/debugger.py
zendriver_flare_bypasser/cdp/device_access.py
zendriver_flare_bypasser/cdp/device_orientation.py
zendriver_flare_bypasser/cdp/dom.py
zendriver_flare_bypasser/cdp/dom_debugger.py
zendriver_flare_bypasser/cdp/dom_snapshot.py
zendriver_flare_bypasser/cdp/dom_storage.py
zendriver_flare_bypasser/cdp/emulation.py
zendriver_flare_bypasser/cdp/event_breakpoints.py
zendriver_flare_bypasser/cdp/extensions.py
zendriver_flare_bypasser/cdp/fed_cm.py
zendriver_flare_bypasser/cdp/fetch.py
zendriver_flare_bypasser/cdp/file_system.py
zendriver_flare_bypasser/cdp/headless_experimental.py
zendriver_flare_bypasser/cdp/heap_profiler.py
zendriver_flare_bypasser/cdp/indexed_db.py
zendriver_flare_bypasser/cdp/input_.py
zendriver_flare_bypasser/cdp/inspector.py
zendriver_flare_bypasser/cdp/io.py
zendriver_flare_bypasser/cdp/layer_tree.py
zendriver_flare_bypasser/cdp/log.py
zendriver_flare_bypasser/cdp/media.py
zendriver_flare_bypasser/cdp/memory.py
zendriver_flare_bypasser/cdp/network.py
zendriver_flare_bypasser/cdp/overlay.py
zendriver_flare_bypasser/cdp/page.py
zendriver_flare_bypasser/cdp/performance.py
zendriver_flare_bypasser/cdp/performance_timeline.py
zendriver_flare_bypasser/cdp/preload.py
zendriver_flare_bypasser/cdp/profiler.py
zendriver_flare_bypasser-0.2.7.dist-info/METADATA
zendriver_flare_bypasser-0.2.7.dist-info/WHEEL
zendriver_flare_bypasser-0.2.7.dist-info/licenses/LICENSE
zendriver_flare_bypasser-0.2.7.dist-info/RECORD
